bsstatus/__init__.py
bsstatus/__main__.py
bsstatus/config.py
bsstatus/status.py
bsstatus-0.0.5.dist-info/licenses/LICENSE.md
bsstatus-0.0.5.dist-info/METADATA
bsstatus-0.0.5.dist-info/WHEEL
bsstatus-0.0.5.dist-info/entry_points.txt
bsstatus-0.0.5.dist-info/top_level.txt
bsstatus-0.0.5.dist-info/RECORD
