Metadata-Version: 2.4
Name: bsstatus
Version: 0.0.5
Summary: A project for bsstatus
Author-email: csm10495 <csm10495@gmail.com>
License-Expression: MIT
Project-URL: homepage, https://github.com/csm10495/bsstatus
Project-URL: repository, https://github.com/csm10495/bsstatus
Project-URL: documentation, https://csm10495.github.io/bsstatus
Classifier: Intended Audience :: Developers
Classifier: Natural Language :: English
Classifier: Operating System :: POSIX
Classifier: Operating System :: Microsoft :: Windows
Classifier: Programming Language :: Python
Classifier: Programming Language :: Python :: 3
Requires-Python: >=3.10
License-File: LICENSE.md
Requires-Dist: cachetools
Requires-Dist: icalendar
Requires-Dist: platformdirs
Requires-Dist: pydantic>2
Requires-Dist: recurring-ical-events
Requires-Dist: requests
Requires-Dist: slack_sdk
Requires-Dist: tzlocal>=4
Provides-Extra: dev
Requires-Dist: pytest; extra == "dev"
Dynamic: license-file
